capybara/__init__.py
capybara/counter.py
capybara/enumerator.py
capybara/generator.py
capybara/interface.py
capybara/worker.py
capybara/equivalence/__init__.py
capybara/equivalence/analyze_one_equivalence.py
capybara/equivalence/enumerate_classes.py
capybara/equivalence/equivalence_class.py
capybara/equivalence/event_reconciliator.py
capybara/equivalence/event_vector.py
capybara/equivalence/event_vector_inverse.py
capybara/equivalence/poly_enum_class.py
capybara/eucalypt/__init__.py
capybara/eucalypt/cyclicity.py
capybara/eucalypt/enumerator.py
capybara/eucalypt/nexparser.py
capybara/eucalypt/reconciliator.py
capybara/eucalypt/solution.py
capybara/eucalypt/tree.py
capybara/eucalypt/util.py
capybara/test/__init__.py
capybara/test/test_count_classes.py
capybara/test/test_count_event_partitions.py
capybara/test/test_counting.py
capybara/test/test_enum_classes.py
capybara/test/test_enum_event_partitions.py
capybara/test/test_event_vectors.py
capybara/test/test_worker.py
capybara_cophylogeny-0.0.9.dist-info/METADATA
capybara_cophylogeny-0.0.9.dist-info/WHEEL
capybara_cophylogeny-0.0.9.dist-info/top_level.txt
capybara_cophylogeny-0.0.9.dist-info/RECORD
