Metadata-Version: 2.1
Name: capybara-cophylogeny
Version: 0.0.9
Summary: Capybara Python package for phylogenetic tree reconciliation
Home-page: https://github.com/Helio-Wang/Capybara-app
Author: Hélio Wang
Author-email: helioaimelesoleil@gmail.com
License: UNKNOWN
Platform: UNKNOWN
Classifier: Development Status :: 4 - Beta
Classifier: Intended Audience :: Science/Research
Classifier: Programming Language :: Python :: 3
Classifier: License :: CeCILL-C Free Software License Agreement (CECILL-C)
Classifier: Operating System :: OS Independent
Requires-Python: >=3.6
